MANIFEST.in
README.md
setup.py
PyGran.egg-info/PKG-INFO
PyGran.egg-info/SOURCES.txt
PyGran.egg-info/dependency_links.txt
PyGran.egg-info/not-zip-safe
PyGran.egg-info/requires.txt
PyGran.egg-info/top_level.txt
src/PyGran/__init__.py
src/PyGran/__main__.py
src/PyGran/_version.py
src/PyGran/analysis/__init__.py
src/PyGran/analysis/setup.py
src/PyGran/analysis/PyGranAnalysis/__init__.py
src/PyGran/analysis/PyGranAnalysis/_version.py
src/PyGran/analysis/PyGranAnalysis/contacts.py
src/PyGran/analysis/PyGranAnalysis/core.c
src/PyGran/analysis/PyGranAnalysis/core.py
src/PyGran/analysis/PyGranAnalysis/core.pyx
src/PyGran/analysis/PyGranAnalysis/dynamics.py
src/PyGran/analysis/PyGranAnalysis/equilibrium.py
src/PyGran/analysis/PyGranAnalysis/generator.py
src/PyGran/analysis/PyGranAnalysis/imaging.py
src/PyGran/analysis/PyGranAnalysis/tools.py
src/PyGran/analysis/tests/basics.py
src/PyGran/gui/Plot.py
src/PyGran/gui/SiDEM.py
src/PyGran/gui/__init__.py
src/PyGran/gui/visualize.py
src/PyGran/gui/windows.py
src/PyGran/gui/Icons/AddSS.png
src/PyGran/gui/Icons/AddWall.png
src/PyGran/gui/Icons/Build.png
src/PyGran/gui/Icons/CAAM.png
src/PyGran/gui/Icons/Clear.png
src/PyGran/gui/Icons/Generate.png
src/PyGran/gui/Icons/Go.png
src/PyGran/gui/Icons/Load.png
src/PyGran/gui/Icons/Plot.png
src/PyGran/gui/Icons/PyGran.png
src/PyGran/gui/Icons/Quit.png
src/PyGran/gui/Icons/Run.png
src/PyGran/gui/Icons/Save.png
src/PyGran/gui/Icons/Settings.png
src/PyGran/gui/Icons/X.png
src/PyGran/gui/Settings/Language.py
src/PyGran/gui/Settings/__init__.py
src/PyGran/params/__init__.py
src/PyGran/params/setup.py
src/PyGran/params/PyGranParams/__init__.py
src/PyGran/params/PyGranParams/_version.py
src/PyGran/plotter/__init__.py
src/PyGran/plotter/ovito.py
src/PyGran/plotter/plot2D.py
src/PyGran/plotter/visualize.py
src/PyGran/simulation/__init__.py
src/PyGran/simulation/setup.py
src/PyGran/simulation/PyGranSim/__init__.py
src/PyGran/simulation/PyGranSim/_version.py
src/PyGran/simulation/PyGranSim/dem.py
src/PyGran/simulation/PyGranSim/engine_liggghts.py
src/PyGran/simulation/PyGranSim/model_liggghts.py
src/PyGran/simulation/PyGranSim/models.py
